LICENSE.txt
MANIFEST.in
README.md
pyproject.toml
setup.cfg
src/falcon_logger/__init__.py
src/falcon_logger/cfg.py
src/falcon_logger/constants_version.py
src/falcon_logger/format_base_facet.py
src/falcon_logger/format_elapsed_facet.py
src/falcon_logger/format_none_facet.py
src/falcon_logger/format_prefix_facet.py
src/falcon_logger/logger.py
src/falcon_logger/mode_base_facet.py
src/falcon_logger/mode_immediate_facet.py
src/falcon_logger/mode_normal_facet.py
src/falcon_logger/mode_null_facet.py
src/falcon_logger/mode_ut_facet.py
src/falcon_logger.egg-info/PKG-INFO
src/falcon_logger.egg-info/SOURCES.txt
src/falcon_logger.egg-info/dependency_links.txt
src/falcon_logger.egg-info/top_level.txt