Metadata-Version: 2.4
Name: falcon-logger
Version: 1.3.0
Summary: module for faster python logging
Author-email: "J. Arrizza" <cppgent0@gmail.com>
Maintainer-email: "J. Arrizza" <cppgent0@gmail.com>
License-Expression: MIT
Project-URL: Website, https://arrizza.com/python-falcon-logger
Project-URL: Source, https://bitbucket.org/arrizza-public/falcon-logger/src/master
Project-URL: Download, https://bitbucket.org/arrizza-public/falcon-logger/get/master.zip
Keywords: logger,fast,cross-platform
Classifier: Development Status :: 4 - Beta
Classifier: Environment :: Console
Classifier: Topic :: Utilities
Classifier: Intended Audience :: Developers
Classifier: Programming Language :: Python :: 3.10
Classifier: Programming Language :: Python :: 3.12
Requires-Python: >=3.9
License-File: LICENSE.txt
Dynamic: license-file
